[
  {
    "username": "Jiran",
    "avatar": [
      "https://dl.airtable.com/.attachments/dff7bb800280472b518feea247b9b693/5244f595/014-girl.png"
    ],
    "color": "#556B2F",
    "participation": "2"
  },
  {
    "username": "Yassine",
    "avatar": [
      "https://dl.airtable.com/.attachments/e0eaecead78d43660323a2d3a294a265/225da840/021-peach.png"
    ],
    "color": "#556B2F",
    "participation": "1"
  },
  {
    "username": "Ahahah",
    "avatar": [
      "https://dl.airtable.com/.attachments/cb662a502c727b06c257a16dedd502d4/c6f7e4d7/012-boy.png"
    ],
    "color": "#556B2F",
    "participation": "2"
  },
  {
    "username": "Alexis7777",
    "avatar": [
      "https://dl.airtable.com/.attachments/cb662a502c727b06c257a16dedd502d4/c6f7e4d7/012-boy.png"
    ],
    "color": "#556B2F",
    "participation": "2"
  },
  {
    "username": "Alexis11",
    "avatar": [
      "https://dl.airtable.com/.attachments/cb662a502c727b06c257a16dedd502d4/c6f7e4d7/012-boy.png"
    ],
    "color": "#556B2F",
    "participation": "2"
  },
  {
    "username": "Raymond",
    "avatar": [
      "https://dl.airtable.com/.attachments/a3f73720a6011c72042b9be85b90006d/cf09d368/046-man.png"
    ],
    "color": "#556B2F",
    "participation": "2"
  },
  {
    "username": "sylvain",
    "avatar": [
      "https://dl.airtable.com/.attachments/cb662a502c727b06c257a16dedd502d4/c6f7e4d7/012-boy.png"
    ],
    "color": "#556B2F",
    "participation": "1"
  },
  {
    "username": "Qiudan",
    "avatar": [
      "https://dl.airtable.com/.attachments/4912e1ebbc150187a3fa81f3c03cca77/2d77402c/006-butterfly.png"
    ],
    "color": "#e9ffdb",
    "participation": "2"
  },
  {
    "username": "Alexis",
    "avatar": [
      "https://dl.airtable.com/.attachments/cb662a502c727b06c257a16dedd502d4/c6f7e4d7/012-boy.png"
    ],
    "color": "#556B2F",
    "participation": "2"
  },
  {
    "username": "Huiyang",
    "avatar": [
      "https://dl.airtable.com/.attachments/0631535bc3c0bcdf52db6a43c9add2d0/525ce2f3/047-flower.png"
    ],
    "color": "#556B2F",
    "participation": "2"
  }
]